odoo/addons/shopinvader_delivery_instruction/__init__.py
odoo/addons/shopinvader_delivery_instruction/__manifest__.py
odoo/addons/shopinvader_delivery_instruction/i18n/shopinvader_delivery_instruction.pot
odoo/addons/shopinvader_delivery_instruction/services/__init__.py
odoo/addons/shopinvader_delivery_instruction/services/abstract_sale.py
odoo/addons/shopinvader_delivery_instruction/services/cart.py
odoo/addons/shopinvader_delivery_instruction/tests/__init__.py
odoo/addons/shopinvader_delivery_instruction/tests/test_sale_order_picking_note.py
odoo12_addon_shopinvader_delivery_instruction-12.0.1.0.0.99.dev2.dist-info/METADATA
odoo12_addon_shopinvader_delivery_instruction-12.0.1.0.0.99.dev2.dist-info/WHEEL
odoo12_addon_shopinvader_delivery_instruction-12.0.1.0.0.99.dev2.dist-info/top_level.txt
odoo12_addon_shopinvader_delivery_instruction-12.0.1.0.0.99.dev2.dist-info/RECORD
